motion_learning_toolbox/__init__.py
motion_learning_toolbox/canonicalize_quaternions.py
motion_learning_toolbox/fix_controller_mapping.py
motion_learning_toolbox/resample.py
motion_learning_toolbox/to_acceleration.py
motion_learning_toolbox/to_body_relative.py
motion_learning_toolbox/to_velocity.py
motion_learning_toolbox-1.0.7.dist-info/licenses/License.md
motion_learning_toolbox-1.0.7.dist-info/METADATA
motion_learning_toolbox-1.0.7.dist-info/WHEEL
motion_learning_toolbox-1.0.7.dist-info/top_level.txt
motion_learning_toolbox-1.0.7.dist-info/RECORD
