Metadata-Version: 2.4
Name: motion-learning-toolbox
Version: 1.0.7
Summary: Python library for preprocessing of XR motion tracking data for machine learning applications.
Author-email: Christian Rack <mail@chrisrack.de>, Lukas Schach <mail.lukas@schach.one>
License: This work by Christian Rack, Lukas Schach and Marc E. Latoschik is licensed under the Creative Commons Attribution-NonCommercial-ShareAlike 4.0 International License. To view a copy of this license, visit http://creativecommons.org/licenses/by-nc-sa/4.0/ or send a letter to Creative Commons, PO Box 1866, Mountain View, CA 94042, USA.
Project-URL: GitHub Repository, https://github.com/cschell/Motion-Learning-Toolbox
Keywords: motion_data,preprocessing
Classifier: Programming Language :: Python
Classifier: Programming Language :: Python :: 3
Requires-Python: >=3.9
License-File: License.md
Requires-Dist: numpy
Requires-Dist: pandas
Requires-Dist: scipy
Requires-Dist: quaternionic
Provides-Extra: dev
Requires-Dist: black; extra == "dev"
Requires-Dist: isort; extra == "dev"
Requires-Dist: pip-tools; extra == "dev"
Requires-Dist: pytest; extra == "dev"
Dynamic: license-file
